texterra/__init__.py
texterra/api.py
texterra/syntaxtree.py
texterra/utils.py
texterra/feature/__init__.py
texterra/feature/disambiguation.py
texterra/feature/keyconcepts.py
texterra/feature/languagedetection.py
texterra/feature/lemmatization.py
texterra/feature/namedentities.py
texterra/feature/polaritydetection.py
texterra/feature/postagging.py
texterra/feature/sentencedetection.py
texterra/feature/spellingcorrection.py
texterra/feature/subjectivitydetection.py
texterra/feature/syntaxdetection.py
texterra/feature/tokenization.py
texterra/tests/__init__.py
texterra/tests/test_ispras.py
texterra-1.0.1.dist-info/DESCRIPTION.rst
texterra-1.0.1.dist-info/METADATA
texterra-1.0.1.dist-info/RECORD
texterra-1.0.1.dist-info/WHEEL
texterra-1.0.1.dist-info/metadata.json
texterra-1.0.1.dist-info/top_level.txt
