Metadata-Version: 2.0
Name: texterra
Version: 1.0.1
Summary: API for natural language processing.
Home-page: https://texterra.ispras.ru
Author: Tsolak Ghukasyan
Author-email: texterra@ispras.ru
License: Apache License, Version 2.0
Keywords: natural language processing,nlp,text processing,parsing,tagging,tokenizing,syntax,language,lemmatization,named entity recognition,spelling correction,sentiment analysis,disambiguation,key concepts detection
Platform: UNKNOWN
Classifier: Intended Audience :: Science/Research
Classifier: Intended Audience :: Developers
Classifier: License :: OSI Approved :: Apache Software License
Classifier: Programming Language :: Python
Classifier: Topic :: Software Development
Classifier: Topic :: Scientific/Engineering
Classifier: Topic :: Scientific/Engineering :: Artificial Intelligence
Classifier: Topic :: Text Processing
Classifier: Topic :: Text Processing :: Linguistic
Classifier: Operating System :: OS Independent
Classifier: Natural Language :: English
Classifier: Natural Language :: Russian
Classifier: Programming Language :: Python :: 2
Classifier: Programming Language :: Python :: 3
Requires-Dist: requests
Requires-Dist: six
